forage/__init__.py
forage/auth.py
forage/cli.py
forage/exporter.py
forage/models.py
forage/parser.py
forage/scraper.py
foragefacebook-1.0.8.dist-info/METADATA
foragefacebook-1.0.8.dist-info/WHEEL
foragefacebook-1.0.8.dist-info/entry_points.txt
foragefacebook-1.0.8.dist-info/licenses/LICENSE
foragefacebook-1.0.8.dist-info/RECORD
