Metadata-Version: 2.4
Name: ForageFacebook
Version: 1.0.8
Summary: CLI tool to scrape posts, comments, and reactions from private Facebook groups
Project-URL: Homepage, https://github.com/jwmoss/forage
Project-URL: Repository, https://github.com/jwmoss/forage
Project-URL: Documentation, https://github.com/jwmoss/forage#readme
Project-URL: Issues, https://github.com/jwmoss/forage/issues
Project-URL: Changelog, https://github.com/jwmoss/forage/blob/master/CHANGELOG.md
Author-email: jwmoss <jwmoss@users.noreply.github.com>
License-Expression: MPL-2.0
License-File: LICENSE
Keywords: automation,cli,facebook,playwright,scraper
Classifier: Development Status :: 4 - Beta
Classifier: Environment :: Console
Classifier: Intended Audience :: Developers
Classifier: License :: OSI Approved :: Mozilla Public License 2.0 (MPL 2.0)
Classifier: Operating System :: OS Independent
Classifier: Programming Language :: Python :: 3
Classifier: Programming Language :: Python :: 3.10
Classifier: Programming Language :: Python :: 3.11
Classifier: Programming Language :: Python :: 3.12
Classifier: Topic :: Internet :: WWW/HTTP :: Browsers
Classifier: Topic :: Utilities
Requires-Python: >=3.10
Requires-Dist: click>=8.0
Requires-Dist: playwright>=1.40
Requires-Dist: pydantic>=2.0
Requires-Dist: rich>=13.0
Provides-Extra: dev
Requires-Dist: pytest-asyncio>=0.23; extra == 'dev'
Requires-Dist: pytest>=8.0; extra == 'dev'
Requires-Dist: ty>=0.0.1a6; extra == 'dev'
